Metadata-Version: 1.0
Name: careerjet-api-client
Version: 3.0.1
Summary: Python interface to Careerjet's public search API
Home-page: http://github.com/careerjet/careerjet-api-client-python
Author: Careerjet
Author-email: UNKNOWN
License: MIT
Platform: UNKNOWN
